agent_gantry/README.md
agent_gantry/__init__.py
agent_gantry/adapters/README.md
agent_gantry/adapters/__init__.py
agent_gantry/adapters/llm_client.py
agent_gantry/adapters/embedders/README.md
agent_gantry/adapters/embedders/__init__.py
agent_gantry/adapters/embedders/base.py
agent_gantry/adapters/embedders/nomic.py
agent_gantry/adapters/embedders/openai.py
agent_gantry/adapters/embedders/simple.py
agent_gantry/adapters/executors/README.md
agent_gantry/adapters/executors/__init__.py
agent_gantry/adapters/executors/a2a_executor.py
agent_gantry/adapters/executors/base.py
agent_gantry/adapters/executors/mcp_client.py
agent_gantry/adapters/rerankers/README.md
agent_gantry/adapters/rerankers/__init__.py
agent_gantry/adapters/rerankers/base.py
agent_gantry/adapters/rerankers/cohere.py
agent_gantry/adapters/tool_spec/__init__.py
agent_gantry/adapters/tool_spec/base.py
agent_gantry/adapters/tool_spec/providers.py
agent_gantry/adapters/tool_spec/registry.py
agent_gantry/adapters/vector_stores/README.md
agent_gantry/adapters/vector_stores/__init__.py
agent_gantry/adapters/vector_stores/base.py
agent_gantry/adapters/vector_stores/lancedb.py
agent_gantry/adapters/vector_stores/memory.py
agent_gantry/adapters/vector_stores/remote.py
agent_gantry/cli/README.md
agent_gantry/cli/__init__.py
agent_gantry/cli/__main__.py
agent_gantry/cli/main.py
agent_gantry/core/README.md
agent_gantry/core/__init__.py
agent_gantry/core/context.py
agent_gantry/core/executor.py
agent_gantry/core/gantry.py
agent_gantry/core/rate_limiter.py
agent_gantry/core/registry.py
agent_gantry/core/router.py
agent_gantry/core/security.py
agent_gantry/integrations/README.md
agent_gantry/integrations/__init__.py
agent_gantry/integrations/anthropic_features.py
agent_gantry/integrations/anthropic_skills.py
agent_gantry/integrations/framework_adapters.py
agent_gantry/integrations/semantic_tools.py
agent_gantry/metrics/README.md
agent_gantry/metrics/__init__.py
agent_gantry/metrics/token_usage.py
agent_gantry-0.1.2.dist-info/METADATA
agent_gantry-0.1.2.dist-info/WHEEL
agent_gantry-0.1.2.dist-info/entry_points.txt
agent_gantry-0.1.2.dist-info/licenses/LICENSE
agent_gantry-0.1.2.dist-info/RECORD
