Metadata-Version: 2.4
Name: agent-gantry
Version: 0.1.2
Summary: Universal Tool Orchestration Platform - Intelligent, secure tool orchestration for LLM-based agent systems
Project-URL: Homepage, https://github.com/CodeHalwell/Agent-Gantry
Project-URL: Repository, https://github.com/CodeHalwell/Agent-Gantry
Author: Agent-Gantry Contributors
License-Expression: MIT
License-File: LICENSE
Keywords: agents,llm,mcp,orchestration,semantic-routing,tools
Classifier: Development Status :: 3 - Alpha
Classifier: Intended Audience :: Developers
Classifier: License :: OSI Approved :: MIT License
Classifier: Programming Language :: Python :: 3
Classifier: Programming Language :: Python :: 3.10
Classifier: Programming Language :: Python :: 3.11
Classifier: Programming Language :: Python :: 3.12
Classifier: Topic :: Software Development :: Libraries :: Python Modules
Requires-Python: >=3.10
Requires-Dist: beautifulsoup4>=4.14.3
Requires-Dist: cryptography>=46.0.3
Requires-Dist: jsonschema>=4.25.1
Requires-Dist: matplotlib>=3.10.8
Requires-Dist: numpy>=2.2.6
Requires-Dist: pandas>=2.3.3
Requires-Dist: pillow>=12.0.0
Requires-Dist: psutil>=7.1.3
Requires-Dist: pydantic>=2.0.0
Requires-Dist: pypdf2>=3.0.1
Requires-Dist: python-barcode>=0.16.1
Requires-Dist: python-docx>=1.2.0
Requires-Dist: pytz>=2025.2
Requires-Dist: pyyaml>=6.0.0
Requires-Dist: qrcode>=8.2
Requires-Dist: scikit-learn>=1.7.2
Requires-Dist: textblob>=0.19.0
Requires-Dist: ty>=0.0.5
Provides-Extra: a2a
Requires-Dist: fastapi>=0.104.0; extra == 'a2a'
Requires-Dist: httpx>=0.24.0; extra == 'a2a'
Requires-Dist: uvicorn>=0.24.0; extra == 'a2a'
Provides-Extra: agent-frameworks
Requires-Dist: agent-framework>=1.0.0b251120; extra == 'agent-frameworks'
Requires-Dist: autogen-agentchat>=0.7.5; extra == 'agent-frameworks'
Requires-Dist: autogen-ext[openai]>=0.7.5; extra == 'agent-frameworks'
Requires-Dist: crewai>=1.6.1; extra == 'agent-frameworks'
Requires-Dist: google-adk>=1.14.1; extra == 'agent-frameworks'
Requires-Dist: langchain-openai>=1.1.6; extra == 'agent-frameworks'
Requires-Dist: langchain>=1.2.0; extra == 'agent-frameworks'
Requires-Dist: langgraph>=1.0.5; extra == 'agent-frameworks'
Requires-Dist: llama-index-core>=0.14.10; extra == 'agent-frameworks'
Requires-Dist: llama-index-llms-openai>=0.6.12; extra == 'agent-frameworks'
Requires-Dist: pyautogen>=0.10.0; extra == 'agent-frameworks'
Requires-Dist: semantic-kernel>=1.30.0; extra == 'agent-frameworks'
Provides-Extra: all
Requires-Dist: agent-framework>=1.0.0b251120; extra == 'all'
Requires-Dist: anthropic>=0.40.0; extra == 'all'
Requires-Dist: asyncpg>=0.29.0; extra == 'all'
Requires-Dist: autogen-agentchat>=0.7.5; extra == 'all'
Requires-Dist: autogen-ext[openai]>=0.7.5; extra == 'all'
Requires-Dist: chromadb>=0.4.0; extra == 'all'
Requires-Dist: cohere>=5.0.0; extra == 'all'
Requires-Dist: crewai>=1.6.1; extra == 'all'
Requires-Dist: einops>=0.8.1; extra == 'all'
Requires-Dist: fastapi>=0.104.0; extra == 'all'
Requires-Dist: google-adk>=1.14.1; extra == 'all'
Requires-Dist: google-cloud-aiplatform>=1.70.0; extra == 'all'
Requires-Dist: google-genai>=1.0.0; extra == 'all'
Requires-Dist: groq>=0.13.0; extra == 'all'
Requires-Dist: httpx>=0.24.0; extra == 'all'
Requires-Dist: huggingface-hub[hf-xet]>=0.36.0; extra == 'all'
Requires-Dist: lancedb>=0.4.0; extra == 'all'
Requires-Dist: langchain-openai>=1.1.6; extra == 'all'
Requires-Dist: langchain>=1.2.0; extra == 'all'
Requires-Dist: langgraph>=1.0.5; extra == 'all'
Requires-Dist: llama-index-core>=0.14.10; extra == 'all'
Requires-Dist: llama-index-llms-openai>=0.6.12; extra == 'all'
Requires-Dist: mcp>=1.0.0; extra == 'all'
Requires-Dist: mistralai>=1.0.0; extra == 'all'
Requires-Dist: mypy>=1.0.0; extra == 'all'
Requires-Dist: numpy>=1.24.0; extra == 'all'
Requires-Dist: openai>=1.0.0; extra == 'all'
Requires-Dist: pint>=0.24.4; extra == 'all'
Requires-Dist: pubchempy>=1.0.5; extra == 'all'
Requires-Dist: pyarrow>=14.0.1; extra == 'all'
Requires-Dist: pyautogen>=0.10.0; extra == 'all'
Requires-Dist: pytest-asyncio>=0.21.0; extra == 'all'
Requires-Dist: pytest-cov>=4.0.0; extra == 'all'
Requires-Dist: pytest>=7.0.0; extra == 'all'
Requires-Dist: python-dotenv>=1.0.0; extra == 'all'
Requires-Dist: python-dotenv>=1.2.1; extra == 'all'
Requires-Dist: qdrant-client>=1.7.0; extra == 'all'
Requires-Dist: rdkit>=2025.9.3; extra == 'all'
Requires-Dist: requests>=2.31.0; extra == 'all'
Requires-Dist: ruff>=0.1.0; extra == 'all'
Requires-Dist: semantic-kernel>=1.30.0; extra == 'all'
Requires-Dist: sentence-transformers>=2.2.0; extra == 'all'
Requires-Dist: sympy>=1.14.0; extra == 'all'
Requires-Dist: uvicorn>=0.24.0; extra == 'all'
Provides-Extra: anthropic
Requires-Dist: anthropic>=0.40.0; extra == 'anthropic'
Provides-Extra: chroma
Requires-Dist: chromadb>=0.4.0; extra == 'chroma'
Provides-Extra: cohere
Requires-Dist: cohere>=5.0.0; extra == 'cohere'
Provides-Extra: dev
Requires-Dist: mypy>=1.0.0; extra == 'dev'
Requires-Dist: pytest-asyncio>=0.21.0; extra == 'dev'
Requires-Dist: pytest-cov>=4.0.0; extra == 'dev'
Requires-Dist: pytest>=7.0.0; extra == 'dev'
Requires-Dist: python-dotenv>=1.0.0; extra == 'dev'
Requires-Dist: ruff>=0.1.0; extra == 'dev'
Provides-Extra: embeddings
Requires-Dist: numpy>=1.24.0; extra == 'embeddings'
Requires-Dist: sentence-transformers>=2.2.0; extra == 'embeddings'
Provides-Extra: example-tools
Requires-Dist: einops>=0.8.1; extra == 'example-tools'
Requires-Dist: huggingface-hub[hf-xet]>=0.36.0; extra == 'example-tools'
Requires-Dist: pint>=0.24.4; extra == 'example-tools'
Requires-Dist: pubchempy>=1.0.5; extra == 'example-tools'
Requires-Dist: python-dotenv>=1.2.1; extra == 'example-tools'
Requires-Dist: rdkit>=2025.9.3; extra == 'example-tools'
Requires-Dist: requests>=2.31.0; extra == 'example-tools'
Requires-Dist: sympy>=1.14.0; extra == 'example-tools'
Provides-Extra: google-genai
Requires-Dist: google-genai>=1.0.0; extra == 'google-genai'
Provides-Extra: google-vertexai
Requires-Dist: google-cloud-aiplatform>=1.70.0; extra == 'google-vertexai'
Provides-Extra: groq
Requires-Dist: groq>=0.13.0; extra == 'groq'
Provides-Extra: lancedb
Requires-Dist: lancedb>=0.4.0; extra == 'lancedb'
Requires-Dist: pyarrow>=14.0.1; extra == 'lancedb'
Provides-Extra: llm-providers
Requires-Dist: anthropic>=0.40.0; extra == 'llm-providers'
Requires-Dist: google-cloud-aiplatform>=1.70.0; extra == 'llm-providers'
Requires-Dist: google-genai>=1.0.0; extra == 'llm-providers'
Requires-Dist: groq>=0.13.0; extra == 'llm-providers'
Requires-Dist: mistralai>=1.0.0; extra == 'llm-providers'
Requires-Dist: openai>=1.0.0; extra == 'llm-providers'
Provides-Extra: mcp
Requires-Dist: mcp>=1.0.0; extra == 'mcp'
Provides-Extra: mistral
Requires-Dist: mistralai>=1.0.0; extra == 'mistral'
Provides-Extra: nomic
Requires-Dist: einops>=0.8.1; extra == 'nomic'
Requires-Dist: numpy>=1.24.0; extra == 'nomic'
Requires-Dist: sentence-transformers>=2.2.0; extra == 'nomic'
Provides-Extra: openai
Requires-Dist: openai>=1.0.0; extra == 'openai'
Provides-Extra: pgvector
Requires-Dist: asyncpg>=0.29.0; extra == 'pgvector'
Provides-Extra: qdrant
Requires-Dist: qdrant-client>=1.7.0; extra == 'qdrant'
Provides-Extra: vector-stores
Requires-Dist: asyncpg>=0.29.0; extra == 'vector-stores'
Requires-Dist: chromadb>=0.4.0; extra == 'vector-stores'
Requires-Dist: qdrant-client>=1.7.0; extra == 'vector-stores'
